LICENSE
MANIFEST.in
Makefile
README.md
setup.cfg
setup.py
tox.ini
Chalice_GraphQL.egg-info/PKG-INFO
Chalice_GraphQL.egg-info/SOURCES.txt
Chalice_GraphQL.egg-info/dependency_links.txt
Chalice_GraphQL.egg-info/not-zip-safe
Chalice_GraphQL.egg-info/requires.txt
Chalice_GraphQL.egg-info/top_level.txt
chalice_graphql/__init__.py
chalice_graphql/graphqlview.py
tests/__init__.py
tests/app.py
tests/schema.py
tests/test_graphiqlview.py
tests/test_graphqlview.py