Metadata-Version: 2.1
Name: Chalice-GraphQL
Version: 0.1.0
Summary: Adds GraphQL support to your Chalice application
Home-page: https://github.com/jrbeilke/chalice-graphql
Author: Jon Beilke
Author-email: jrbeilke@gmail.com
License: MIT
Download-URL: https://github.com/jrbeilke/chalice-graphql/releases
Keywords: api graphql protocol rest chalice
Platform: any
Classifier: Development Status :: 4 - Beta
Classifier: Intended Audience :: Developers
Classifier: Topic :: Software Development :: Libraries
Classifier: Programming Language :: Python :: 3.6
Classifier: Programming Language :: Python :: 3.7
Classifier: Programming Language :: Python :: 3.8
Classifier: License :: OSI Approved :: MIT License
Provides-Extra: test
Provides-Extra: dev
